gentrace/__init__.py
gentrace/_base_client.py
gentrace/_client.py
gentrace/_compat.py
gentrace/_constants.py
gentrace/_exceptions.py
gentrace/_files.py
gentrace/_models.py
gentrace/_qs.py
gentrace/_resource.py
gentrace/_response.py
gentrace/_streaming.py
gentrace/_types.py
gentrace/_version.py
gentrace/py.typed
gentrace/_utils/__init__.py
gentrace/_utils/_logs.py
gentrace/_utils/_proxy.py
gentrace/_utils/_reflection.py
gentrace/_utils/_resources_proxy.py
gentrace/_utils/_streams.py
gentrace/_utils/_sync.py
gentrace/_utils/_transform.py
gentrace/_utils/_typing.py
gentrace/_utils/_utils.py
gentrace/lib/client_handles.py
gentrace/lib/client_instance.py
gentrace/lib/constants.py
gentrace/lib/custom_otlp_exporter.py
gentrace/lib/eval.py
gentrace/lib/eval_dataset.py
gentrace/lib/experiment.py
gentrace/lib/experiment_control.py
gentrace/lib/init.py
gentrace/lib/interaction.py
gentrace/lib/otel_setup.py
gentrace/lib/pipeline_validation.py
gentrace/lib/progress.py
gentrace/lib/sampler.py
gentrace/lib/span_processor.py
gentrace/lib/traced.py
gentrace/lib/types.py
gentrace/lib/utils.py
gentrace/lib/validation.py
gentrace/lib/vendored_otlp_exporter.py
gentrace/lib/warnings.py
gentrace/resources/__init__.py
gentrace/resources/datasets.py
gentrace/resources/experiments.py
gentrace/resources/organizations.py
gentrace/resources/pipelines.py
gentrace/resources/test_cases.py
gentrace/types/__init__.py
gentrace/types/dataset.py
gentrace/types/dataset_create_params.py
gentrace/types/dataset_list.py
gentrace/types/dataset_list_params.py
gentrace/types/dataset_update_params.py
gentrace/types/experiment.py
gentrace/types/experiment_create_params.py
gentrace/types/experiment_list.py
gentrace/types/experiment_list_params.py
gentrace/types/experiment_update_params.py
gentrace/types/organization.py
gentrace/types/pipeline.py
gentrace/types/pipeline_create_params.py
gentrace/types/pipeline_list.py
gentrace/types/pipeline_list_params.py
gentrace/types/pipeline_update_params.py
gentrace_py-1.6.1.dist-info/METADATA
gentrace_py-1.6.1.dist-info/WHEEL
gentrace_py-1.6.1.dist-info/licenses/LICENSE
gentrace_py-1.6.1.dist-info/RECORD
