Metadata-Version: 2.3
Name: gentrace-py
Version: 1.6.1
Summary: The official Python library for the gentrace API
Project-URL: Homepage, https://github.com/gentrace/gentrace-python
Project-URL: Repository, https://github.com/gentrace/gentrace-python
Author-email: Gentrace <support@gentrace.ai>
License: MIT
Classifier: Intended Audience :: Developers
Classifier: License :: OSI Approved :: MIT License
Classifier: Operating System :: MacOS
Classifier: Operating System :: Microsoft :: Windows
Classifier: Operating System :: OS Independent
Classifier: Operating System :: POSIX
Classifier: Operating System :: POSIX :: Linux
Classifier: Programming Language :: Python :: 3.8
Classifier: Programming Language :: Python :: 3.9
Classifier: Programming Language :: Python :: 3.10
Classifier: Programming Language :: Python :: 3.11
Classifier: Programming Language :: Python :: 3.12
Classifier: Programming Language :: Python :: 3.13
Classifier: Topic :: Software Development :: Libraries :: Python Modules
Classifier: Typing :: Typed
Requires-Python: >=3.8
Requires-Dist: anyio<5,>=3.5.0
Requires-Dist: distro<2,>=1.7.0
Requires-Dist: httpx<1,>=0.23.0
Requires-Dist: opentelemetry-exporter-otlp-proto-http>=1.21.0
Requires-Dist: opentelemetry-instrumentation>=0.41b0
Requires-Dist: opentelemetry-processor-baggage>=0.45.0b0
Requires-Dist: opentelemetry-sdk>=1.21.0
Requires-Dist: pydantic<3,>=1.9.0
Requires-Dist: rich>=14.0.0
Requires-Dist: sniffio
Requires-Dist: tomli>=1.2.0; python_version < '3.11'
Requires-Dist: typing-extensions<5,>=4.10
Provides-Extra: aiohttp
Requires-Dist: aiohttp; extra == 'aiohttp'
Requires-Dist: httpx-aiohttp>=0.1.6; extra == 'aiohttp'
Provides-Extra: anthropic
Requires-Dist: anthropic; extra == 'anthropic'
Provides-Extra: langchain
Requires-Dist: langchain-core>=0.1.0; extra == 'langchain'
Requires-Dist: openinference-instrumentation-langchain>=0.1.0; extra == 'langchain'
Provides-Extra: openai
Requires-Dist: openai; extra == 'openai'
Requires-Dist: openinference-instrumentation-openai; extra == 'openai'
Provides-Extra: openai-agents
Requires-Dist: openai-agents>=0.1.0; extra == 'openai-agents'
Requires-Dist: openinference-instrumentation-openai-agents; extra == 'openai-agents'
Provides-Extra: pydantic-ai
Requires-Dist: pydantic-ai>=0.2.14; extra == 'pydantic-ai'
